PyFoam/Error.py
PyFoam/FoamInformation.py
PyFoam/__init__.py
PyFoam/Applications/APoMaFoXiiQt.py
PyFoam/Applications/AddCaseDataToDatabase.py
PyFoam/Applications/Benchmark.py
PyFoam/Applications/BinarySize.py
PyFoam/Applications/BlockMeshConverter.py
PyFoam/Applications/BlockMeshRewrite.py
PyFoam/Applications/BuildHelper.py
PyFoam/Applications/CaseBuilder.py
PyFoam/Applications/CaseBuilderBackend.py
PyFoam/Applications/CaseReport.py
PyFoam/Applications/ChangeBoundaryName.py
PyFoam/Applications/ChangeBoundaryType.py
PyFoam/Applications/ChangePython.py
PyFoam/Applications/ClearBoundaryValue.py
PyFoam/Applications/ClearCase.py
PyFoam/Applications/ClearInternalField.py
PyFoam/Applications/CloneCase.py
PyFoam/Applications/ClusterTester.py
PyFoam/Applications/CommonBlink1.py
PyFoam/Applications/CommonCaseBuilder.py
PyFoam/Applications/CommonChangeBoundary.py
PyFoam/Applications/CommonClearCase.py
PyFoam/Applications/CommonLibFunctionTrigger.py
PyFoam/Applications/CommonMultiRegion.py
PyFoam/Applications/CommonParallel.py
PyFoam/Applications/CommonParserOptions.py
PyFoam/Applications/CommonPickledDataInput.py
PyFoam/Applications/CommonPlotLines.py
PyFoam/Applications/CommonPlotOptions.py
PyFoam/Applications/CommonPrePostHooks.py
PyFoam/Applications/CommonReadWriteCSV.py
PyFoam/Applications/CommonReportRunnerData.py
PyFoam/Applications/CommonReportUsage.py
PyFoam/Applications/CommonRestart.py
PyFoam/Applications/CommonSafeTrigger.py
PyFoam/Applications/CommonSelectTimesteps.py
PyFoam/Applications/CommonServer.py
PyFoam/Applications/CommonStandardOutput.py
PyFoam/Applications/CommonTemplateBehaviour.py
PyFoam/Applications/CommonTemplateFormat.py
PyFoam/Applications/CommonVCSCommit.py
PyFoam/Applications/CommonWriteAllTrigger.py
PyFoam/Applications/Comparator.py
PyFoam/Applications/CompareDictionary.py
PyFoam/Applications/CompressCaseFiles.py
PyFoam/Applications/ConvertToCSV.py
PyFoam/Applications/CopyLastToFirst.py
PyFoam/Applications/CreateBoundaryPatches.py
PyFoam-2022.9.dist-info/COPYING
PyFoam-2022.9.dist-info/METADATA
PyFoam-2022.9.dist-info/WHEEL
PyFoam-2022.9.dist-info/top_level.txt
PyFoam-2022.9.dist-info/RECORD
