Metadata-Version: 2.1
Name: PyFoam
Version: 2022.9
Summary: Python Utilities for OpenFOAM
Home-page: http://openfoamwiki.net/index.php/Contrib/PyFoam
Author: Bernhard F.W. Gschaider
Author-email: bgschaid@hfd-research.com
License: GPL
Keywords: cfd openfoam
Platform: UNKNOWN
Classifier: Development Status :: 5 - Production/Stable
Classifier: Intended Audience :: Science/Research
Classifier: Topic :: Scientific/Engineering
Classifier: License :: OSI Approved :: GNU General Public License v2 or later (GPLv2+)
Classifier: Programming Language :: Python :: 2
Classifier: Programming Language :: Python :: 2.6
Classifier: Programming Language :: Python :: 2.7
Classifier: Programming Language :: Python :: 3
Classifier: Programming Language :: Python :: 3.2
Classifier: Programming Language :: Python :: 3.3
Classifier: Programming Language :: Python :: 3.4
Classifier: Programming Language :: Python :: 3.5
Classifier: Programming Language :: Python :: 3.6
Classifier: Programming Language :: Python :: 3.7
Classifier: Programming Language :: Python :: 3.8
Classifier: Programming Language :: Python :: 3.9
License-File: COPYING
Requires-Dist: numpy
